[
  {
    "label": "Publish Movies",
    "name": "movies",
    "publishApiKey":"movie",
    "contentIdKey": "externalId",
    "noItemsText": "No movies have been assigned",
    "searchPlaceholder": "Search By Title, External Id",
    "assignedSearchPlaceholder": "Search Movies",
    "deleteTitle": "Delete Movie",
    "deleteModalDescription": "Do you want to remove this movie from the assigned listing?",
    "selectedItemsTitle": "Movie",
    "selectedItemsButtonText": "Movie",
    "itemButtonText": "Movie",
    "availableText": "Publish Movie",
    "showAddButton": true,
    "addButtonText": "Add Movies",
    "showInputField": true,
    "showFilterButton": true,
    "showMarkDone": true,
    "addPageTitle": "Add Movies",
    "fetched": false,
    "visible": true
  },
  {
    "label": "Publish Videos",
    "name": "videos",
    "publishApiKey":"video",
    "contentIdKey": "externalId",
    "noItemsText": "No videos have been assigned",
    "searchPlaceholder": "Search By Title, External Id",
    "assignedSearchPlaceholder": "Search Videos",
    "deleteTitle": "Delete Video",
    "deleteModalDescription": "Do you want to remove this video from the assigned listing?",
    "selectedItemsTitle": "Video",
    "selectedItemsButtonText": "Video",
    "itemButtonText": "Video",
    "availableText": "Available Videos",
    "showAddButton": true,
    "addButtonText": "Add Videos",
    "showInputField": true,
    "showFilterButton": true,
    "showMarkDone": true,
    "addPageTitle": "Add Videos",
    "fetched": false,
    "visible": true
  },
  {
    "label": "Publish TV Shows",
    "name": "tvShows",
    "publishApiKey":"tvShow",
    "contentIdKey": "externalId",
    "noItemsText": "No tv shows have been assigned",
    "searchPlaceholder": "Search By Title, External Id",
    "assignedSearchPlaceholder": "Search TV Shows",
    "deleteTitle": "Delete TV Show",
    "deleteModalDescription": "Do you want to remove this tv show from the assigned listing?",
    "selectedItemsTitle": "TV Shows",
    "selectedItemsButtonText": "TV Show",
    "itemButtonText": "TV Show",
    "availableText": "Available TV Shows",
    "showAddButton": true,
    "addButtonText": "Add TV Shows",
    "showInputField": true,
    "showFilterButton": true,
    "showMarkDone": true,
    "addPageTitle": "Add TV Shows",
    "fetched": false,
    "visible": true
  },
  {
    "label": "Publish Seasons",
    "name": "seasons",
    "publishApiKey":"season",
    "contentIdKey": "externalId",
    "noItemsText": "No Seasons have been assigned",
    "searchPlaceholder": "Search By Title, External Id",
    "assignedSearchPlaceholder": "Search Seasons",
    "deleteTitle": "Delete Season",
    "deleteModalDescription": "Do you want to remove this season from the assigned listing?",
    "selectedItemsTitle": "Seasons",
    "selectedItemsButtonText": "Season",
    "itemButtonText": "Season",
    "availableText": "Available Seasons",
    "showAddButton": true,
    "addButtonText": "Add Seasons",
    "showInputField": true,
    "showFilterButton": true,
    "showMarkDone": true,
    "addPageTitle": "Add Seasons",
    "fetched": false,
    "visible": true
  },
  {
    "label": "Publish Episodes",
    "name": "episodes",
    "publishApiKey":"episode",
    "contentIdKey": "episodeExternalId",
    "noItemsText": "No Episodes have been assigned",
    "searchPlaceholder": "Search By Title, External Id",
    "assignedSearchPlaceholder": "Search Episodes",
    "deleteTitle": "Delete Episode",
    "deleteModalDescription": "Do you want to remove this episode from the assigned listing?",
    "selectedItemsTitle": "Episodes",
    "selectedItemsButtonText": "Episode",
    "itemButtonText": "Episode",
    "availableText": "Available Episodes",
    "showAddButton": true,
    "addButtonText": "Add Episodes",
    "showInputField": true,
    "showFilterButton": true,
    "showMarkDone": true,
    "addPageTitle": "Add Episodes",
    "fetched": false,
    "visible": true
  }
]